odoo_restart/__init__.py
odoo_restart/restart.py
odoo_restart-0.1.1.dist-info/METADATA
odoo_restart-0.1.1.dist-info/WHEEL
odoo_restart-0.1.1.dist-info/entry_points.txt
odoo_restart-0.1.1.dist-info/top_level.txt
odoo_restart-0.1.1.dist-info/RECORD
